gql_pic4ser/__init__.py
gql_pic4ser-0.1.1.dist-info/METADATA
gql_pic4ser-0.1.1.dist-info/WHEEL
gql_pic4ser-0.1.1.dist-info/top_level.txt
gql_pic4ser-0.1.1.dist-info/RECORD
