Metadata-Version: 2.1
Name: gql-pic4ser
Version: 0.1.1
Summary: GraphQL ROS API for PiC4Ser
Home-page: https://github.com/pic4ser-kubernetes/gql-pic4ser
Author-email: matteo.ghia@yahoo.it
Keywords: pic4ser,graphql,ros
Classifier: Development Status :: 5 - Production/Stable
Classifier: Operating System :: POSIX :: Linux
Classifier: Intended Audience :: Developers
Classifier: Natural Language :: English
Classifier: Programming Language :: Python :: 3
Classifier: Programming Language :: Python :: 3.8
Classifier: Programming Language :: Python :: 3.9
Classifier: Programming Language :: Python :: 3.10
Classifier: Programming Language :: Python :: 3.11
Classifier: Topic :: Internet :: WWW/HTTP
Classifier: Topic :: Internet :: WWW/HTTP :: Dynamic Content
Requires-Python: ~=3.8
Requires-Dist: gql[requests]
